plover_yaml_dictionary.py
plover_yaml_dictionary-0.0.1.dist-info/DESCRIPTION.rst
plover_yaml_dictionary-0.0.1.dist-info/METADATA
plover_yaml_dictionary-0.0.1.dist-info/RECORD
plover_yaml_dictionary-0.0.1.dist-info/WHEEL
plover_yaml_dictionary-0.0.1.dist-info/entry_points.txt
plover_yaml_dictionary-0.0.1.dist-info/metadata.json
plover_yaml_dictionary-0.0.1.dist-info/top_level.txt
plover_yaml_dictionary-0.0.1.dist-info/zip-safe
